{"eventid":"ipphoney.connect","timestamp":"2022-05-09T07:07:21.669182Z","url":"/","src_ip":"178.62.99.151","src_port":61953,"dst_port":631,"sensor":"7a65b25995cd","request":"GET","dst_ip":"172.31.0.2"}
{"eventid":"ipphoney.get-printer-attributes","operation":"Get-Printer-Attributes","timestamp":"2022-05-09T07:15:39.087265Z","url":"/ipp","src_ip":"167.94.145.59","src_port":55154,"dst_port":631,"sensor":"7a65b25995cd","request":"POST","query":{"version":"2.1","request_id":"00000001","operation":"Get-Printer-Attributes","groups":[{"group_type":"Operation-Attributes-Tag","attributes":[{"attribute_type":"charset","attribute_name":"attributes-charset","attribute_value":["utf-8"]},{"attribute_type":"language","attribute_name":"attributes-natural-language","attribute_value":["en-us"]},{"attribute_type":"uri","attribute_name":"printer-uri","attribute_value":["ipp://34.121.180.85:631/ipp"]},{"attribute_type":"keyword","attribute_name":"requested-attributes","attribute_value":["all"]}]}]},"user_agent":"Mozilla/5.0 (compatible; CensysInspect/1.1; +https://about.censys.io/)","dst_ip":"172.31.0.2"}
